dotkeeper/__init__.py
dotkeeper/__main__.py
dotkeeper/constants.py
dotkeeper/exceptions.py
dotkeeper/config/base.py
dotkeeper/utils/byte_size.py
dotkeeper/utils/common.py
dotkeeper-0.1.0a1.dist-info/METADATA
dotkeeper-0.1.0a1.dist-info/WHEEL
dotkeeper-0.1.0a1.dist-info/entry_points.txt
dotkeeper-0.1.0a1.dist-info/licenses/LICENSE.txt
dotkeeper-0.1.0a1.dist-info/RECORD
